lhvqt/__init__.py
lhvqt/lhvqt.py
lhvqt/lhvqt_comb.py
lhvqt/lvqt.py
lhvqt/lvqt_hilb.py
lhvqt/lvqt_orig.py
lhvqt/lvqt_real.py
lhvqt/utils.py
lhvqt/variational.py
lhvqt-0.5.3.dist-info/LICENSE.txt
lhvqt-0.5.3.dist-info/METADATA
lhvqt-0.5.3.dist-info/WHEEL
lhvqt-0.5.3.dist-info/top_level.txt
lhvqt-0.5.3.dist-info/RECORD
