Metadata-Version: 2.1
Name: lhvqt
Version: 0.5.3
Summary: Frontend filterbank learning module with HVQT initialization capabilities
Home-page: https://github.com/cwitkowitz/LHVQT
Author: Frank Cwitkowitz
Author-email: fcwitkow@ur.rochester.edu
License: MIT
Requires-Python: >=3.7
License-File: LICENSE.txt
Requires-Dist: numpy
Requires-Dist: librosa
Requires-Dist: torch
Requires-Dist: matplotlib
Requires-Dist: soundfile
